twistedchecker/__init__.py
twistedchecker/checkers/__init__.py
twistedchecker/checkers/comment.py
twistedchecker/checkers/docstring.py
twistedchecker/checkers/formattingoperation.py
twistedchecker/checkers/header.py
twistedchecker/checkers/names.py
twistedchecker/checkers/patch_pylint_format.py
twistedchecker/checkers/testclassname.py
twistedchecker/configuration/pylintrc
twistedchecker/core/__init__.py
twistedchecker/core/exceptionfinder.py
twistedchecker/core/runner.py
twistedchecker/core/util.py
twistedchecker/functionaltests/__init__.py
twistedchecker/functionaltests/argumentname.py
twistedchecker/functionaltests/argumentname.result
twistedchecker/functionaltests/attributename.py
twistedchecker/functionaltests/attributename.result
twistedchecker/functionaltests/blanklines_pass.result
twistedchecker/functionaltests/classname_fail.py
twistedchecker/functionaltests/classname_fail.result
twistedchecker/functionaltests/classname_pass.py
twistedchecker/functionaltests/classname_pass.result
twistedchecker/functionaltests/comments.py
twistedchecker/functionaltests/comments.result
twistedchecker/functionaltests/constname.py
twistedchecker/functionaltests/constname.result
twistedchecker/functionaltests/copyright_fail.py
twistedchecker/functionaltests/copyright_fail.result
twistedchecker/functionaltests/copyright_oneline_fail.py
twistedchecker/functionaltests/copyright_oneline_fail.result
twistedchecker/functionaltests/copyright_pass.py
twistedchecker/functionaltests/copyright_pass.result
twistedchecker/functionaltests/copyright_reversed_fail.py
twistedchecker/functionaltests/copyright_reversed_fail.result
twistedchecker/functionaltests/docstring_fail.py
twistedchecker/functionaltests/docstring_fail.result
twistedchecker/functionaltests/docstring_pass.py
twistedchecker/functionaltests/docstring_pass.result
twistedchecker/functionaltests/formattingoperation.py
twistedchecker/functionaltests/formattingoperation.result
twistedchecker/functionaltests/functionname_fail.py
twistedchecker-0.7.4.dist-info/LICENSE
twistedchecker-0.7.4.dist-info/METADATA
twistedchecker-0.7.4.dist-info/WHEEL
twistedchecker-0.7.4.dist-info/entry_points.txt
twistedchecker-0.7.4.dist-info/top_level.txt
twistedchecker-0.7.4.dist-info/RECORD
