Metadata-Version: 2.1
Name: twistedchecker
Version: 0.7.4
Summary: A Twisted coding standard compliance checker.
Home-page: https://github.com/twisted/twistedchecker
Author: Twisted Matrix Laboratories
Author-email: twisted-python@twistedmatrix.com
License: MIT
Keywords: twisted,checker,compliance,pep8
Platform: UNKNOWN
Classifier: Development Status :: 3 - Alpha
Classifier: Environment :: Console
Classifier: Intended Audience :: Developers
Classifier: License :: OSI Approved :: MIT License
Classifier: Programming Language :: Python
Classifier: Programming Language :: Python :: 3
Classifier: Programming Language :: Python :: 3 :: Only
Classifier: Programming Language :: Python :: 3.5
Classifier: Programming Language :: Python :: 3.6
Classifier: Programming Language :: Python :: 3.7
Classifier: Topic :: Software Development :: Quality Assurance
Requires-Dist: pylint (>=2.4.4)
Requires-Dist: twisted (>=15.0.0)
Provides-Extra: dev
Requires-Dist: pyflakes ; extra == 'dev'
Requires-Dist: coverage ; extra == 'dev'
